CONTRIBUTING.md
LICENSE
MANIFEST.in
README.md
settings.ini
setup.py
fastinferenz/__init__.py
fastinferenz/_nbdev.py
fastinferenz/class_confusion.py
fastinferenz/onnx.py
fastinferenz/soft_dependencies.py
fastinferenz.egg-info/PKG-INFO
fastinferenz.egg-info/SOURCES.txt
fastinferenz.egg-info/dependency_links.txt
fastinferenz.egg-info/entry_points.txt
fastinferenz.egg-info/not-zip-safe
fastinferenz.egg-info/requires.txt
fastinferenz.egg-info/top_level.txt
fastinferenz/inference/__init__.py
fastinferenz/inference/export.py
fastinferenz/inference/inference.py
fastinferenz/inference/text.py
fastinferenz/tabular/__init__.py
fastinferenz/tabular/core.py
fastinferenz/tabular/interpretation.py
fastinferenz/tabular/pd.py
fastinferenz/tabular/waterfall.py
fastinferenz/tabular/shap/__init__.py
fastinferenz/tabular/shap/core.py
fastinferenz/tabular/shap/interp.py